new/__init__.py
new/line.py
pp_new-1.3.dist-info/METADATA
pp_new-1.3.dist-info/WHEEL
pp_new-1.3.dist-info/entry_points.txt
pp_new-1.3.dist-info/top_level.txt
pp_new-1.3.dist-info/RECORD
